{
  "updatedAt": "2026-06-11T21:16:40+08:00",
  "categories": {
    "废铜": {
      "1号光亮铜线": 91.2,
      "紫铜": 89.75,
      "黄铜": 56.2,
      "铜管": 90.0,
      "铜排": 91,
      "铜米": 68.5,
      "杂铜": 46.0,
      "铜屑": 76.0
    },
    "废铝": {
      "铝线": 21.05,
      "熟铝": 19.75,
      "生铝": 17.1,
      "铝合金": 17.6,
      "铝板": 21.1,
      "铝型材": 19.2,
      "铝箔": 17.6,
      "铝屑": 17.7
    },
    "废铁": {
      "重废": 2.03,
      "中废": 2.15,
      "轻废": 1.8,
      "钢筋": 2.4,
      "铸铁": 2.25,
      "铁皮": 1.75,
      "铁屑": 1.79,
      "生铁": 1.73
    },
    "废不锈钢": {
      "316不锈钢": 21.7,
      "304不锈钢": 10.45,
      "201不锈钢": 4.9,
      "不锈钢屑": 5.0,
      "杂不锈钢": 3.45
    },
    "废纸": {
      "A4纸": 1.85,
      "报纸": 2.57,
      "纸箱": 1.83,
      "书本纸": 2.52,
      "花纸": 0.6,
      "杂纸": 0.5
    },
    "废塑料": {
      "ABS": 5.8,
      "PP": 2.6,
      "PE": 1.2,
      "PVC": 1.8,
      "PET": 4.2,
      "杂塑料": 1.6
    },
    "废玻璃": {
      "钢化玻璃": 0.8,
      "平板玻璃": 0.7,
      "碎玻璃": 0.56,
      "玻璃瓶": 0.25
    },
    "废轮胎": {
      "工程胎": 1.8,
      "钢丝胎": 1.8,
      "尼龙胎": 1.25,
      "自行车胎": 0.8
    },
    "废电池": {
      "镍氢电池": 18,
      "锂电池": 21.55,
      "铅酸电池": 9.75,
      "干电池": 1.0
    },
    "其他": {
      "废电子板": 7.6,
      "废电机": 4.5,
      "废电线": 25,
      "废家电": 3.5,
      "杂料": 1.5
    }
  }
}